pipeline_turbo/__init__.py
pipeline_turbo/turbo.py
pipeline_turbo-0.0.6.dist-info/METADATA
pipeline_turbo-0.0.6.dist-info/WHEEL
pipeline_turbo-0.0.6.dist-info/top_level.txt
pipeline_turbo-0.0.6.dist-info/RECORD
