Metadata-Version: 2.1
Name: pipeline-turbo
Version: 0.0.6
Summary: Accelerate your processing pipeline
Home-page: https://github.com/dreji18/pipeline-turbo
Author: Deepak John Reji, Afreen Aman
Author-email: deepakjohn1994@gmail.com
License: MIT
Classifier: License :: OSI Approved :: MIT License
Classifier: Programming Language :: Python :: 3.6
Classifier: Programming Language :: Python :: 3.7
Classifier: Programming Language :: Python :: 3.8
Classifier: Programming Language :: Python :: 3.9
Requires-Dist: tqdm
